{"trial_id": "0591", "hyperparameters": {"space": [{"class_name": "Int", "config": {"name": "num_layers", "default": null, "conditions": [], "min_value": 3, "max_value": 6, "step": 1, "sampling": "linear"}}, {"class_name": "Int", "config": {"name": "units_0", "default": null, "conditions": [], "min_value": 32, "max_value": 256, "step": 32, "sampling": "linear"}}, {"class_name": "Int", "config": {"name": "units_1", "default": null, "conditions": [], "min_value": 32, "max_value": 256, "step": 32, "sampling": "linear"}}, {"class_name": "Int", "config": {"name": "units_2", "default": null, "conditions": [], "min_value": 32, "max_value": 256, "step": 32, "sampling": "linear"}}, {"class_name": "Choice", "config": {"name": "learning_rate", "default": 0.01, "conditions": [], "values": [0.01, 0.001, 0.0001], "ordered": true}}, {"class_name": "Int", "config": {"name": "units_3", "default": null, "conditions": [], "min_value": 32, "max_value": 256, "step": 32, "sampling": "linear"}}, {"class_name": "Int", "config": {"name": "units_4", "default": null, "conditions": [], "min_value": 32, "max_value": 256, "step": 32, "sampling": "linear"}}, {"class_name": "Int", "config": {"name": "units_5", "default": null, "conditions": [], "min_value": 32, "max_value": 256, "step": 32, "sampling": "linear"}}], "values": {"num_layers": 3, "units_0": 96, "units_1": 64, "units_2": 224, "learning_rate": 0.01, "units_3": 160, "units_4": 224, "units_5": 32, "tuner/epochs": 34, "tuner/initial_epoch": 12, "tuner/bracket": 4, "tuner/round": 2, "tuner/trial_id": "0547"}}, "metrics": {"metrics": {"loss": {"direction": "min", "observations": [{"value": [725.0133666992188], "step": 21}]}, "root_mean_squared_error": {"direction": "min", "observations": [{"value": [26.862680435180664], "step": 21}]}, "val_loss": {"direction": "min", "observations": [{"value": [622.4570922851562], "step": 21}]}, "val_root_mean_squared_error": {"direction": "min", "observations": [{"value": [24.880638122558594], "step": 21}]}, "lr": {"direction": "min", "observations": [{"value": [0.0010025883093476295], "step": 21}]}}}, "score": 24.880638122558594, "best_step": 21, "status": "COMPLETED", "message": null}